einsum_pipe/__init__.py
einsum_pipe/einsum_pipe.py
einsum_pipe/einsum_script.py
einsum_pipe/ops.py
einsum_pipe-0.3.1.dist-info/METADATA
einsum_pipe-0.3.1.dist-info/WHEEL
einsum_pipe-0.3.1.dist-info/licenses/LICENSE
einsum_pipe-0.3.1.dist-info/RECORD
