Metadata-Version: 2.1
Name: einsum_pipe
Version: 0.3.1
Summary: A Python package to compile multiple Numpy einsum operations into one
Project-URL: Homepage, https://github.com/davystrong/Einsum-Pipe
Project-URL: Bug Tracker, https://github.com/davystrong/Einsum-Pipe/issues
Author: David Armstrong
License-File: LICENSE
Classifier: License :: OSI Approved :: MIT License
Classifier: Operating System :: OS Independent
Classifier: Programming Language :: Python :: 3
Requires-Python: >=3.7
Requires-Dist: numpy
Requires-Dist: opt-einsum
